Compiled from "TestLambda.java"
class TestLambda {
  private int i;

  TestLambda();
    Code:
       0: aload_0
       1: invokespecial #1                  // Method java/lang/Object."<init>":()V
       4: return

  private static void testLambda();
    Code:
       0: bipush        40
       2: istore_0
       3: new           #7                  // class TestLambda
       6: dup
       7: invokespecial #9                  // Method "<init>":()V
      10: astore_1
      11: aload_1
      12: bipush        10
      14: putfield      #10                 // Field i:I
      17: aload_1
      18: iload_0
      19: invokedynamic #14,  0             // InvokeDynamic #0:applyAsInt:(LTestLambda;I)Ljava/util/function/IntUnaryOperator;
      24: astore_2
      25: getstatic     #18                 // Field java/lang/System.out:Ljava/io/PrintStream;
      28: aload_2
      29: iconst_2
      30: invokeinterface #24,  2           // InterfaceMethod java/util/function/IntUnaryOperator.applyAsInt:(I)I
      35: invokevirtual #29                 // Method java/io/PrintStream.println:(I)V
      38: return

  private static void testLambda1();
    Code:
       0: invokedynamic #35,  0             // InvokeDynamic #1:applyAsInt:()Ljava/util/function/IntBinaryOperator;
       5: astore_0
       6: getstatic     #18                 // Field java/lang/System.out:Ljava/io/PrintStream;
       9: aload_0
      10: iconst_2
      11: bipush        40
      13: invokeinterface #38,  3           // InterfaceMethod java/util/function/IntBinaryOperator.applyAsInt:(II)I
      18: invokevirtual #29                 // Method java/io/PrintStream.println:(I)V
      21: return

  private static void testLambda2();
    Code:
       0: bipush        40
       2: istore_0
       3: iload_0
       4: invokedynamic #43,  0             // InvokeDynamic #2:applyAsInt:(I)Ljava/util/function/IntUnaryOperator;
       9: astore_1
      10: getstatic     #18                 // Field java/lang/System.out:Ljava/io/PrintStream;
      13: aload_1
      14: iconst_2
      15: invokeinterface #24,  2           // InterfaceMethod java/util/function/IntUnaryOperator.applyAsInt:(I)I
      20: invokevirtual #29                 // Method java/io/PrintStream.println:(I)V
      23: return

  private static void testLambda3();
    Code:
       0: ldc2_w        #46                 // double 40.0d
       3: dstore_0
       4: dload_0
       5: invokedynamic #48,  0             // InvokeDynamic #3:apply:(D)Ljava/util/function/Function;
      10: astore_2
      11: getstatic     #18                 // Field java/lang/System.out:Ljava/io/PrintStream;
      14: aload_2
      15: iconst_2
      16: invokestatic  #52                 // Method java/lang/Integer.valueOf:(I)Ljava/lang/Integer;
      19: invokeinterface #58,  2           // InterfaceMethod java/util/function/Function.apply:(Ljava/lang/Object;)Ljava/lang/Object;
      24: invokevirtual #63                 // Method java/io/PrintStream.println:(Ljava/lang/Object;)V
      27: return

  private static void testMethodRef();
    Code:
       0: invokedynamic #66,  0             // InvokeDynamic #4:applyAsInt:()Ljava/util/function/IntBinaryOperator;
       5: astore_0
       6: getstatic     #18                 // Field java/lang/System.out:Ljava/io/PrintStream;
       9: aload_0
      10: iconst_2
      11: bipush        40
      13: invokeinterface #38,  3           // InterfaceMethod java/util/function/IntBinaryOperator.applyAsInt:(II)I
      18: invokevirtual #29                 // Method java/io/PrintStream.println:(I)V
      21: return

  private static void testMethodRef2();
    Code:
       0: invokedynamic #67,  0             // InvokeDynamic #5:apply:()Ljava/util/function/BiFunction;
       5: astore_0
       6: getstatic     #18                 // Field java/lang/System.out:Ljava/io/PrintStream;
       9: aload_0
      10: iconst_2
      11: invokestatic  #52                 // Method java/lang/Integer.valueOf:(I)Ljava/lang/Integer;
      14: bipush        40
      16: invokestatic  #52                 // Method java/lang/Integer.valueOf:(I)Ljava/lang/Integer;
      19: invokeinterface #70,  3           // InterfaceMethod java/util/function/BiFunction.apply:(Ljava/lang/Object;Ljava/lang/Object;)Ljava/lang/Object;
      24: invokevirtual #63                 // Method java/io/PrintStream.println:(Ljava/lang/Object;)V
      27: return

  private static byte methodRef(double);
    Code:
       0: bipush        40
       2: dload_0
       3: d2i
       4: iadd
       5: i2b
       6: ireturn

  private static void testMethodRef3();
    Code:
       0: invokedynamic #75,  0             // InvokeDynamic #6:applyAsInt:()Ljava/util/function/IntUnaryOperator;
       5: astore_0
       6: getstatic     #18                 // Field java/lang/System.out:Ljava/io/PrintStream;
       9: aload_0
      10: iconst_2
      11: invokeinterface #24,  2           // InterfaceMethod java/util/function/IntUnaryOperator.applyAsInt:(I)I
      16: invokevirtual #29                 // Method java/io/PrintStream.println:(I)V
      19: return

  static void testMethodRef4();
    Code:
       0: iconst_2
       1: anewarray     #78                 // class java/lang/String
       4: dup
       5: iconst_0
       6: ldc           #80                 // String A
       8: aastore
       9: dup
      10: iconst_1
      11: ldc           #82                 // String B
      13: aastore
      14: astore_0
      15: aload_0
      16: invokestatic  #84                 // Method java/util/Arrays.stream:([Ljava/lang/Object;)Ljava/util/stream/Stream;
      19: invokedynamic #90,  0             // InvokeDynamic #7:accept:()Ljava/util/function/Consumer;
      24: invokeinterface #94,  2           // InterfaceMethod java/util/stream/Stream.forEach:(Ljava/util/function/Consumer;)V
      29: return

  public static void main(java.lang.String[]);
    Code:
       0: invokestatic  #100                // Method testLambda:()V
       3: invokestatic  #103                // Method testLambda1:()V
       6: invokestatic  #106                // Method testLambda2:()V
       9: invokestatic  #109                // Method testLambda3:()V
      12: invokestatic  #112                // Method testMethodRef:()V
      15: invokestatic  #115                // Method testMethodRef2:()V
      18: invokestatic  #118                // Method testMethodRef3:()V
      21: invokestatic  #121                // Method testMethodRef4:()V
      24: return

  private static void lambda$testMethodRef4$4(java.lang.String);
    Code:
       0: getstatic     #18                 // Field java/lang/System.out:Ljava/io/PrintStream;
       3: aload_0
       4: invokevirtual #124                // Method java/io/PrintStream.println:(Ljava/lang/String;)V
       7: return

  private static java.lang.Double lambda$testLambda3$3(double, java.lang.Integer);
    Code:
       0: aload_2
       1: invokevirtual #127                // Method java/lang/Integer.intValue:()I
       4: i2d
       5: dload_0
       6: dadd
       7: invokestatic  #131                // Method java/lang/Double.valueOf:(D)Ljava/lang/Double;
      10: areturn

  private static int lambda$testLambda2$2(int, int);
    Code:
       0: iload_1
       1: iload_0
       2: iadd
       3: ireturn

  private static int lambda$testLambda1$1(int, int);
    Code:
       0: iload_0
       1: iload_1
       2: iadd
       3: ireturn

  private static int lambda$testLambda$0(TestLambda, int, int);
    Code:
       0: aload_0
       1: getfield      #10                 // Field i:I
       4: iload_2
       5: iadd
       6: iload_1
       7: iadd
       8: ireturn
}
